nashypy/__init__.py
nashypy/lrsnash.py
nashypy/games/2x2_avis.txt
nashypy/games/2x2_battle.txt
nashypy/games/2x2_chicken.txt
nashypy/games/2x2_onemixed_nopure.txt
nashypy/games/2x2_onepurenash.txt
nashypy/games/2x2_stable_unstable_mixed.txt
nashypy/games/2x2_staghunt.txt
nashypy/games/2x2_twopurenash.txt
nashypy/games/2x2_zerosum.txt
nashypy/games/3x2_game1.txt
nashypy/games/3x2_game2.txt
nashypy/games/3x3_rockpaperscissor.txt
tests/__init__.py
tests/test_module.py
nashypy-0.0.2.dist-info/LICENSE
nashypy-0.0.2.dist-info/METADATA
nashypy-0.0.2.dist-info/WHEEL
nashypy-0.0.2.dist-info/top_level.txt
nashypy-0.0.2.dist-info/RECORD
