Metadata-Version: 2.1
Name: nashypy
Version: 0.0.2
Summary: Game Theory Library
Home-page: https://github.com/snpham/nashypy
Author: Son Pham
Author-email: snpham02@gmail.com
Classifier: Programming Language :: Python :: 3
Classifier: License :: OSI Approved :: MIT License
Classifier: Operating System :: OS Independent
License-File: LICENSE
Requires-Dist: plotly
Requires-Dist: numpy
Requires-Dist: sympy
Requires-Dist: matplotlib
